[{"username":"Smith","startdate":"10/12/19","starttime":"0900","hours":4},{"username":"Steve","startdate":"none","starttime":"none","hours":0},{"username":"John","startdate":"none","starttime":"none","hours":0},{"username":"Frank","startdate":"none","starttime":"none","hours":0},{"username":"Louie","startdate":"none","starttime":"none","hours":0},{"username":"slip","startdate":"none","starttime":"none","hours":0},{"username":"asd","startdate":"none","starttime":"none","hours":0},{"username":"sgsgs","startdate":"none","starttime":"none","hours":0},{"username":"hkhh","startdate":"none","starttime":"none","hours":0},{"username":"vsdv","startdate":"none","starttime":"none","hours":0},{"username":"bbb","startdate":"none","starttime":"none","hours":0}]